main.py
test_request_url.py
test_request_url_standalone.py
uv_python_mcp-0.1.0.dist-info/METADATA
uv_python_mcp-0.1.0.dist-info/WHEEL
uv_python_mcp-0.1.0.dist-info/top_level.txt
uv_python_mcp-0.1.0.dist-info/RECORD
