Metadata-Version: 2.4
Name: uv-python-mcp
Version: 0.1.0
Summary: Add your description here
Requires-Python: >=3.10
Requires-Dist: fastmcp>=2.11.3
